geneval/__init__.py
geneval/framework.py
geneval/llm_manager.py
geneval/schemas.py
geneval/adapters/__init__.py
geneval/adapters/deepeval_adapter.py
geneval/adapters/ragas_adapter.py
gen_eval-0.0.1.dist-info/METADATA
gen_eval-0.0.1.dist-info/WHEEL
gen_eval-0.0.1.dist-info/licenses/LICENSE
gen_eval-0.0.1.dist-info/RECORD
