Metadata-Version: 2.4
Name: gen-eval
Version: 0.0.1
Summary: Project GenEval: A Unified Evaluation Framework for Generative AI Applications
License-File: LICENSE
Requires-Python: >=3.12
Requires-Dist: datasets>=4.0.0
Requires-Dist: deepeval>=3.3.2
Requires-Dist: langchain-anthropic>=0.1.0
Requires-Dist: langchain-community>=0.1.0
Requires-Dist: langchain-google-genai>=0.1.0
Requires-Dist: langchain-openai>=0.1.0
Requires-Dist: langchain>=0.1.0
Requires-Dist: pandas>=2.3.1
Requires-Dist: pillow>=10.0.0
Requires-Dist: pydantic>=2.11.7
Requires-Dist: pytest-cov>=6.2.1
Requires-Dist: pyyaml>=6.0
Requires-Dist: ragas>=0.3.0
Requires-Dist: regex>=2025.2.10
Requires-Dist: safety>=3.2.11
Provides-Extra: dev
Requires-Dist: bandit>=1.7.0; extra == 'dev'
Requires-Dist: black>=24.0.0; extra == 'dev'
Requires-Dist: isort>=5.13.0; extra == 'dev'
Requires-Dist: pip-audit>=2.6.0; extra == 'dev'
Requires-Dist: pre-commit>=3.6.0; extra == 'dev'
Requires-Dist: ruff>=0.1.0; extra == 'dev'
Provides-Extra: test
Requires-Dist: pytest-cov>=4.0.0; extra == 'test'
Requires-Dist: pytest-mock>=3.10.0; extra == 'test'
Requires-Dist: pytest>=7.0.0; extra == 'test'
